{"id_music":1443,"name":"Renova-me","url_image":"\/images\/hasd_502B.jpg","image_position":null,"url_music":"\/musics\/pt\/Corinhos\/Renova-me.mp3","url_instrumental_music":"\/musics\/pt\/Corinhos\/Renova-me - PB.mp3","lyric":[{"id_lyric":31847,"id_music":1443,"lyric":"Renova-me, Senhor Jesus\r\nJ\u00e1 n\u00e3o quero ser igual","aux_lyric":null,"url_image":"\/images\/hasd_502B.jpg","image_position":null,"time":"00:00:17","instrumental_time":"00:00:17","show_slide":1,"order":10},{"id_lyric":31848,"id_music":1443,"lyric":"Renova-me, Senhor Jesus\r\nP\u00f5e em mim Teu cora\u00e7\u00e3o","aux_lyric":null,"url_image":"\/images\/hasd_502B.jpg","image_position":null,"time":"00:00:32","instrumental_time":"00:00:32","show_slide":1,"order":11},{"id_lyric":31849,"id_music":1443,"lyric":"Porque tudo o que\r\nh\u00e1 dentro de mim","aux_lyric":null,"url_image":"\/images\/hasd_502B.jpg","image_position":null,"time":"00:00:48","instrumental_time":"00:00:48","show_slide":1,"order":12},{"id_lyric":31850,"id_music":1443,"lyric":"Necessita ser\r\nmudado Senhor","aux_lyric":null,"url_image":"\/images\/hasd_502B.jpg","image_position":null,"time":"00:00:57","instrumental_time":"00:00:57","show_slide":1,"order":13},{"id_lyric":31851,"id_music":1443,"lyric":"Porque tudo o que h\u00e1\r\ndentro do meu cora\u00e7\u00e3o","aux_lyric":null,"url_image":"\/images\/hasd_502B.jpg","image_position":null,"time":"00:01:05","instrumental_time":"00:01:05","show_slide":1,"order":14},{"id_lyric":31852,"id_music":1443,"lyric":"Necessita mais de Ti","aux_lyric":null,"url_image":"\/images\/hasd_502B.jpg","image_position":null,"time":"00:01:13","instrumental_time":"00:01:13","show_slide":1,"order":15},{"id_lyric":31853,"id_music":1443,"lyric":"","aux_lyric":null,"url_image":"\/images\/hasd_502B.jpg","image_position":null,"time":"00:01:23","instrumental_time":"00:01:23","show_slide":1,"order":16},{"id_lyric":31867,"id_music":1443,"lyric":"Renova-me, Senhor Jesus\r\nJ\u00e1 n\u00e3o quero ser igual","aux_lyric":null,"url_image":"\/images\/hasd_502B.jpg","image_position":null,"time":"00:01:26","instrumental_time":"00:01:26","show_slide":1,"order":20},{"id_lyric":31868,"id_music":1443,"lyric":"Renova-me, Senhor Jesus\r\nP\u00f5e em mim Teu cora\u00e7\u00e3o","aux_lyric":null,"url_image":"\/images\/hasd_502B.jpg","image_position":null,"time":"00:01:41","instrumental_time":"00:01:41","show_slide":1,"order":21},{"id_lyric":31869,"id_music":1443,"lyric":"Porque tudo o que\r\nh\u00e1 dentro de mim","aux_lyric":null,"url_image":"\/images\/hasd_502B.jpg","image_position":null,"time":"00:01:56","instrumental_time":"00:01:56","show_slide":1,"order":22},{"id_lyric":31870,"id_music":1443,"lyric":"Necessita ser\r\nmudado Senhor","aux_lyric":null,"url_image":"\/images\/hasd_502B.jpg","image_position":null,"time":"00:02:05","instrumental_time":"00:02:05","show_slide":1,"order":23},{"id_lyric":31871,"id_music":1443,"lyric":"Porque tudo o que h\u00e1\r\ndentro do meu cora\u00e7\u00e3o","aux_lyric":null,"url_image":"\/images\/hasd_502B.jpg","image_position":null,"time":"00:02:13","instrumental_time":"00:02:13","show_slide":1,"order":24},{"id_lyric":31872,"id_music":1443,"lyric":"Necessita mais de Ti\r\nNecessita mais de Ti","aux_lyric":null,"url_image":"\/images\/hasd_502B.jpg","image_position":null,"time":"00:02:21","instrumental_time":"00:02:21","show_slide":1,"order":25},{"id_lyric":31873,"id_music":1443,"lyric":"","aux_lyric":null,"url_image":"\/images\/hasd_502B.jpg","image_position":null,"time":"00:02:38","instrumental_time":"00:02:38","show_slide":1,"order":26}],"albums":[{"id_album":683,"name":"Corinhos","track":1,"url_image":"\/covers\/corinhos.bmp","order":20}]}