{"id_music":4281,"name":"La hora del Juicio","url_image":"\/images\/hasd_410.jpg","image_position":null,"url_music":"\/musics\/es\/Himnario Adventista\/La hora del Juicio.mp3","url_instrumental_music":"\/musics\/es\/Himnario Adventista\/La hora del Juicio - PB.mp3","lyric":[{"id_lyric":68389,"id_music":4281,"lyric":"Solemne anuncio dios nos da:","aux_lyric":null,"url_image":null,"image_position":null,"time":"00:00:12","instrumental_time":"00:00:13","show_slide":1,"order":1},{"id_lyric":69493,"id_music":4281,"lyric":"Del juicio el tiempo ya lleg\u00f3","aux_lyric":null,"url_image":null,"image_position":null,"time":"00:00:18","instrumental_time":"00:00:20","show_slide":1,"order":2},{"id_lyric":68390,"id_music":4281,"lyric":"Nuestro destino sellar\u00e1","aux_lyric":null,"url_image":null,"image_position":null,"time":"00:00:24","instrumental_time":"00:00:26","show_slide":1,"order":3},{"id_lyric":69494,"id_music":4281,"lyric":"Y cada caso el juez ver\u00e1","aux_lyric":null,"url_image":null,"image_position":null,"time":"00:00:30","instrumental_time":"00:00:33","show_slide":1,"order":4},{"id_lyric":68391,"id_music":4281,"lyric":"Su obra har\u00e1, concluir\u00e1","aux_lyric":null,"url_image":null,"image_position":null,"time":"00:00:36","instrumental_time":"00:00:39","show_slide":1,"order":5},{"id_lyric":69495,"id_music":4281,"lyric":"El juicio investigador","aux_lyric":null,"url_image":null,"image_position":null,"time":"00:00:42","instrumental_time":"00:00:46","show_slide":1,"order":6},{"id_lyric":68392,"id_music":4281,"lyric":"El juez vendr\u00e1\r\ncon gran poder","aux_lyric":null,"url_image":null,"image_position":null,"time":"00:00:48","instrumental_time":"00:00:52","show_slide":1,"order":7},{"id_lyric":69496,"id_music":4281,"lyric":"Y el pago a todos les dar\u00e1","aux_lyric":null,"url_image":null,"image_position":null,"time":"00:00:54","instrumental_time":"00:00:59","show_slide":1,"order":8},{"id_lyric":69307,"id_music":4281,"lyric":"","aux_lyric":null,"url_image":null,"image_position":null,"time":"00:00:00","instrumental_time":"00:00:00","show_slide":0,"order":9},{"id_lyric":68393,"id_music":4281,"lyric":"Aquel que vivo a morir","aux_lyric":null,"url_image":null,"image_position":null,"time":"00:01:01","instrumental_time":"00:01:06","show_slide":1,"order":10},{"id_lyric":69497,"id_music":4281,"lyric":"Y darsepor el pecador","aux_lyric":null,"url_image":null,"image_position":null,"time":"00:01:07","instrumental_time":"00:01:13","show_slide":1,"order":11},{"id_lyric":68394,"id_music":4281,"lyric":"Al cielo luego ascendi\u00f3","aux_lyric":null,"url_image":null,"image_position":null,"time":"00:01:13","instrumental_time":"00:01:20","show_slide":1,"order":12},{"id_lyric":69498,"id_music":4281,"lyric":"Y pronto al mundo volver\u00e1","aux_lyric":null,"url_image":null,"image_position":null,"time":"00:01:19","instrumental_time":"00:01:26","show_slide":1,"order":13},{"id_lyric":68395,"id_music":4281,"lyric":"Es nuestro fiel intercesor","aux_lyric":null,"url_image":null,"image_position":null,"time":"00:01:25","instrumental_time":"00:01:33","show_slide":1,"order":14},{"id_lyric":69499,"id_music":4281,"lyric":"En el santuario celestial","aux_lyric":null,"url_image":null,"image_position":null,"time":"00:01:31","instrumental_time":"00:01:39","show_slide":1,"order":15},{"id_lyric":68396,"id_music":4281,"lyric":"Su sangre all\u00ed abogar\u00e1","aux_lyric":null,"url_image":null,"image_position":null,"time":"00:01:37","instrumental_time":"00:01:46","show_slide":1,"order":16},{"id_lyric":69500,"id_music":4281,"lyric":"Dando a sus hijos el perd\u00f3n","aux_lyric":null,"url_image":null,"image_position":null,"time":"00:01:43","instrumental_time":"00:01:52","show_slide":1,"order":17},{"id_lyric":69308,"id_music":4281,"lyric":"","aux_lyric":null,"url_image":null,"image_position":null,"time":"00:00:00","instrumental_time":"00:00:00","show_slide":0,"order":18},{"id_lyric":68397,"id_music":4281,"lyric":"Solemne hora llegar\u00e1","aux_lyric":null,"url_image":null,"image_position":null,"time":"00:01:50","instrumental_time":"00:02:00","show_slide":1,"order":19},{"id_lyric":69501,"id_music":4281,"lyric":"Y los que aman al se\u00f1or","aux_lyric":null,"url_image":null,"image_position":null,"time":"00:01:56","instrumental_time":"00:02:06","show_slide":1,"order":20},{"id_lyric":68398,"id_music":4281,"lyric":"Ante su juez habr\u00e1n de estar","aux_lyric":null,"url_image":null,"image_position":null,"time":"00:02:02","instrumental_time":"00:02:12","show_slide":1,"order":21},{"id_lyric":69502,"id_music":4281,"lyric":"Y el fallo entonces \u00e9l dar\u00e1","aux_lyric":null,"url_image":null,"image_position":null,"time":"00:02:08","instrumental_time":"00:02:19","show_slide":1,"order":22},{"id_lyric":68399,"id_music":4281,"lyric":"Oh mi jes\u00fas, confio en ti","aux_lyric":null,"url_image":null,"image_position":null,"time":"00:02:14","instrumental_time":"00:02:26","show_slide":1,"order":23},{"id_lyric":69503,"id_music":4281,"lyric":"A tu amor me aferr\u00f3 yo","aux_lyric":null,"url_image":null,"image_position":null,"time":"00:02:20","instrumental_time":"00:02:33","show_slide":1,"order":24},{"id_lyric":68400,"id_music":4281,"lyric":"Mi nombre, tu confiesa hoy","aux_lyric":null,"url_image":null,"image_position":null,"time":"00:02:26","instrumental_time":"00:02:39","show_slide":1,"order":25},{"id_lyric":69504,"id_music":4281,"lyric":"Y mis pecados borra as\u00ed","aux_lyric":null,"url_image":null,"image_position":null,"time":"00:02:32","instrumental_time":"00:02:45","show_slide":1,"order":26},{"id_lyric":69309,"id_music":4281,"lyric":"","aux_lyric":null,"url_image":null,"image_position":null,"time":"00:00:00","instrumental_time":"00:00:00","show_slide":0,"order":27},{"id_lyric":68401,"id_music":4281,"lyric":"Oh, mi se\u00f1or, que pueda hoy","aux_lyric":null,"url_image":null,"image_position":null,"time":"00:02:39","instrumental_time":"00:02:53","show_slide":1,"order":28},{"id_lyric":69505,"id_music":4281,"lyric":"Sentir cu\u00e1n seria hora es","aux_lyric":null,"url_image":null,"image_position":null,"time":"00:02:45","instrumental_time":"00:03:00","show_slide":1,"order":29},{"id_lyric":68402,"id_music":4281,"lyric":"Oh, ll\u00e9name de tu amor","aux_lyric":null,"url_image":null,"image_position":null,"time":"00:02:51","instrumental_time":"00:03:06","show_slide":1,"order":30},{"id_lyric":69506,"id_music":4281,"lyric":"Transformame con tu poder","aux_lyric":null,"url_image":null,"image_position":null,"time":"00:02:57","instrumental_time":"00:03:12","show_slide":1,"order":31},{"id_lyric":68403,"id_music":4281,"lyric":"Confiando en ti\r\ncon gran valor","aux_lyric":null,"url_image":null,"image_position":null,"time":"00:03:03","instrumental_time":"00:03:19","show_slide":1,"order":32},{"id_lyric":69507,"id_music":4281,"lyric":"Yo quiero en la lid vencer","aux_lyric":null,"url_image":null,"image_position":null,"time":"00:03:09","instrumental_time":"00:03:26","show_slide":1,"order":33},{"id_lyric":68404,"id_music":4281,"lyric":"Y un d\u00eda estar contigo en sion","aux_lyric":null,"url_image":null,"image_position":null,"time":"00:03:15","instrumental_time":"00:03:32","show_slide":1,"order":34},{"id_lyric":69508,"id_music":4281,"lyric":"Cantando a ti, mi salvador","aux_lyric":null,"url_image":null,"image_position":null,"time":"00:03:21","instrumental_time":"00:03:39","show_slide":1,"order":35},{"id_lyric":68405,"id_music":4281,"lyric":"","aux_lyric":null,"url_image":null,"image_position":null,"time":"00:03:31","instrumental_time":"00:03:49","show_slide":1,"order":36}],"albums":[{"id_album":713,"name":"Himnario Adventista","track":313,"url_image":"\/covers\/hasd.bmp","order":1}]}