{"id_music":4540,"name":"El pueblo que conoce a su Dios","url_image":"\/images\/hasd_364A.jpg","image_position":null,"url_music":"\/musics\/es\/Himnario Adventista\/El pueblo que conoce a su Dios.mp3","url_instrumental_music":"\/musics\/es\/Himnario Adventista\/El pueblo que conoce a su Dios - PB.mp3","lyric":[{"id_lyric":72227,"id_music":4540,"lyric":"Atardece en el mundo:","aux_lyric":null,"url_image":"\/images\/hasd_364A.jpg","image_position":null,"time":"00:00:21","instrumental_time":"00:00:23","show_slide":1,"order":1},{"id_lyric":72228,"id_music":4540,"lyric":"Hay violencia y maldad","aux_lyric":null,"url_image":"\/images\/hasd_364A.jpg","image_position":null,"time":"00:00:26","instrumental_time":"00:00:28","show_slide":1,"order":2},{"id_lyric":72229,"id_music":4540,"lyric":"Desafiantes las tinieblas","aux_lyric":null,"url_image":"\/images\/hasd_364A.jpg","image_position":null,"time":"00:00:31","instrumental_time":"00:00:34","show_slide":1,"order":3},{"id_lyric":72230,"id_music":4540,"lyric":"Hoy ocultan la verdad","aux_lyric":null,"url_image":"\/images\/hasd_364A.jpg","image_position":null,"time":"00:00:37","instrumental_time":"00:00:40","show_slide":1,"order":4},{"id_lyric":72852,"id_music":4540,"lyric":"","aux_lyric":null,"url_image":"\/images\/hasd_364A.jpg","image_position":null,"time":"00:00:00","instrumental_time":"00:00:00","show_slide":0,"order":5},{"id_lyric":72231,"id_music":4540,"lyric":"\"Mas el pueblo que\r\na su Dios conoce","aux_lyric":null,"url_image":"\/images\/hasd_364B.jpg","image_position":null,"time":"00:00:42","instrumental_time":"00:00:46","show_slide":1,"order":6},{"id_lyric":72232,"id_music":4540,"lyric":"Se esforzar\u00e1 y har\u00e1\"","aux_lyric":null,"url_image":"\/images\/hasd_364B.jpg","image_position":null,"time":"00:00:48","instrumental_time":"00:00:52","show_slide":1,"order":7},{"id_lyric":72233,"id_music":4540,"lyric":"\u00a1De pie, de pie, oh pueblo!","aux_lyric":null,"url_image":"\/images\/hasd_364B.jpg","image_position":null,"time":"00:00:52","instrumental_time":"00:00:57","show_slide":1,"order":8},{"id_lyric":72234,"id_music":4540,"lyric":"\u00a1Conoces a tu Dios!","aux_lyric":null,"url_image":"\/images\/hasd_364B.jpg","image_position":null,"time":"00:00:58","instrumental_time":"00:01:04","show_slide":1,"order":9},{"id_lyric":72235,"id_music":4540,"lyric":"\u00a1Lev\u00e1ntate y concluye","aux_lyric":null,"url_image":"\/images\/hasd_364B.jpg","image_position":null,"time":"00:01:03","instrumental_time":"00:01:09","show_slide":1,"order":10},{"id_lyric":72236,"id_music":4540,"lyric":"La obra que \u00e9l te dio!","aux_lyric":null,"url_image":"\/images\/hasd_364B.jpg","image_position":null,"time":"00:01:09","instrumental_time":"00:01:15","show_slide":1,"order":11},{"id_lyric":72853,"id_music":4540,"lyric":"","aux_lyric":null,"url_image":"\/images\/hasd_364B.jpg","image_position":null,"time":"00:00:00","instrumental_time":"00:00:00","show_slide":0,"order":12},{"id_lyric":72237,"id_music":4540,"lyric":"Atardece en el cielo:","aux_lyric":null,"url_image":"\/images\/hasd_364A.jpg","image_position":null,"time":"00:01:14","instrumental_time":"00:01:21","show_slide":1,"order":13},{"id_lyric":72238,"id_music":4540,"lyric":"Ya la gracia cesar\u00e1","aux_lyric":null,"url_image":"\/images\/hasd_364A.jpg","image_position":null,"time":"00:01:21","instrumental_time":"00:01:28","show_slide":1,"order":14},{"id_lyric":72239,"id_music":4540,"lyric":"Lanza Dios el desaf\u00edo:","aux_lyric":null,"url_image":"\/images\/hasd_364A.jpg","image_position":null,"time":"00:01:26","instrumental_time":"00:01:34","show_slide":1,"order":15},{"id_lyric":72240,"id_music":4540,"lyric":"\u00bfQui\u00e9n mi obra acabar\u00e1?","aux_lyric":null,"url_image":"\/images\/hasd_364A.jpg","image_position":null,"time":"00:01:31","instrumental_time":"00:01:39","show_slide":1,"order":16},{"id_lyric":72854,"id_music":4540,"lyric":"","aux_lyric":null,"url_image":"\/images\/hasd_364A.jpg","image_position":null,"time":"00:00:00","instrumental_time":"00:00:00","show_slide":0,"order":17},{"id_lyric":72241,"id_music":4540,"lyric":"\"Mas el pueblo que\r\na su Dios conoce","aux_lyric":null,"url_image":"\/images\/hasd_364B.jpg","image_position":null,"time":"00:01:36","instrumental_time":"00:01:44","show_slide":1,"order":18},{"id_lyric":72242,"id_music":4540,"lyric":"Se esforzar\u00e1 y har\u00e1\"","aux_lyric":null,"url_image":"\/images\/hasd_364B.jpg","image_position":null,"time":"00:01:42","instrumental_time":"00:01:51","show_slide":1,"order":19},{"id_lyric":72243,"id_music":4540,"lyric":"\u00a1De pie, de pie, oh pueblo!","aux_lyric":null,"url_image":"\/images\/hasd_364B.jpg","image_position":null,"time":"00:01:47","instrumental_time":"00:01:56","show_slide":1,"order":20},{"id_lyric":72244,"id_music":4540,"lyric":"\u00a1Conoces a tu Dios!","aux_lyric":null,"url_image":"\/images\/hasd_364B.jpg","image_position":null,"time":"00:01:53","instrumental_time":"00:02:03","show_slide":1,"order":21},{"id_lyric":72245,"id_music":4540,"lyric":"\u00a1Lev\u00e1ntate y concluye","aux_lyric":null,"url_image":"\/images\/hasd_364B.jpg","image_position":null,"time":"00:01:58","instrumental_time":"00:02:08","show_slide":1,"order":22},{"id_lyric":72246,"id_music":4540,"lyric":"La obra que \u00e9l te dio!","aux_lyric":null,"url_image":"\/images\/hasd_364B.jpg","image_position":null,"time":"00:02:04","instrumental_time":"00:02:15","show_slide":1,"order":23},{"id_lyric":72247,"id_music":4540,"lyric":"","aux_lyric":null,"url_image":"\/images\/hasd_364B.jpg","image_position":null,"time":"00:02:13","instrumental_time":"00:02:24","show_slide":1,"order":25}],"albums":[{"id_album":713,"name":"Himnario Adventista","track":578,"url_image":"\/covers\/hasd.bmp","order":1}]}